{
  "project_info": {
    "project_number": "19311624947",
    "project_id": "unimatch-6283a",
    "storage_bucket": "unimatch-6283a.appspot.com"
  },
  "client": [
    {
      "client_info": {
        "mobilesdk_app_id": "1:19311624947:android:de1f7351207d1f71942d86",
        "android_client_info": {
          "package_name": "com.example.unimatch"
        }
      },
      "oauth_client": [],
      "api_key": [
        {
          "current_key": "AIzaSyDqpsHWUFgiufUveq7IRokavbH8ctemCYQ"
        }
      ],
      "services": {
        "appinvite_service": {
          "other_platform_oauth_client": []
        }
      }
    }
  ],
  "configuration_version": "1"
}